jupyter_forest_extension/__init__.py
jupyter_forest_extension/jupyter_version_check_handler.py
jupyter_forest_extension/jupyter_version_health_handler.py
jupyter_forest_extension/jupyter_version_service.py
jupyter_forest_extension/jupyter_version_update_handler.py
jupyter_forest_extension/logging_service.py
jupyter_forest_extension/process_executor.py
jupyter_forest_extension/qcs_app_public_url_handler.py
jupyter_forest_extension/utc_logging_formatter.py
jupyter_forest_extension/version_check.py
jupyter_forest_extension/version_check_code_handler.py
jupyter_forest_extension/version_check_handler.py
jupyter_forest_extension/version_check_service.py
jupyter_forest_extension/version_update_handler.py
jupyter_forest_extension/data_objects/__init__.py
jupyter_forest_extension/data_objects/docker_image.py
jupyter_forest_extension/data_objects/docker_image_check_result.py
jupyter_forest_extension/data_objects/docker_tag.py
jupyter_forest_extension/data_objects/docker_tag_properties.py
jupyter_forest_extension/data_objects/docker_tags.py
jupyter_forest_extension/data_objects/forest_docker_images.py
jupyter_forest_extension/data_objects/forest_docker_versions.py
jupyter_forest_extension/data_objects/forest_docker_versions_checks_results.py
jupyter_forest_extension/data_objects/forest_version.py
jupyter_forest_extension/data_objects/forest_version_to_check.py
jupyter_forest_extension/data_objects/forest_versions.py
jupyter_forest_extension/data_objects/forest_versions_checks_request.py
jupyter_forest_extension/data_objects/forest_versions_checks_results.py
jupyter_forest_extension/data_objects/get_forest_versions_response.py
jupyter_forest_extension/data_objects/link.py
jupyter_forest_extension/data_objects/post_forest_versions_checks_response.py
jupyter_forest_extension/data_objects/serializable.py
jupyter_forest_extension-0.7.0.dist-info/LICENSE.txt
jupyter_forest_extension-0.7.0.dist-info/METADATA
jupyter_forest_extension-0.7.0.dist-info/NOTICE.rst
jupyter_forest_extension-0.7.0.dist-info/WHEEL
jupyter_forest_extension-0.7.0.dist-info/top_level.txt
jupyter_forest_extension-0.7.0.dist-info/RECORD
