Metadata-Version: 2.1
Name: jupyter-forest-extension
Version: 0.7.0
Summary: Jupyter Notebook extension for Rigetti Forest
Home-page: https://www.rigetti.com
Author: Rigetti Computing
Author-email: soft-apps@rigetti.com
License: Apache-2.0
Platform: UNKNOWN
Classifier: License :: OSI Approved :: Apache Software License
Requires-Dist: docker
Requires-Dist: dotmap
Requires-Dist: notebook
Requires-Dist: tornado
Requires-Dist: simplejson
Requires-Dist: pypi-simple
Requires-Dist: aiohttp
Requires-Dist: cachetools
Requires-Dist: jupyterlab
